<?xml version="1.0" encoding="UTF-8" standalone="yes"?>
<p:sld xmlns:a="http://schemas.openxmlformats.org/drawingml/2006/main" xmlns:r="http://schemas.openxmlformats.org/officeDocument/2006/relationships" xmlns:p="http://schemas.openxmlformats.org/presentationml/2006/main"><p:cSld><p:spTree><p:nvGrpSpPr><p:cNvPr id="1" name=""/><p:cNvGrpSpPr/><p:nvPr/></p:nvGrpSpPr><p:grpSpPr><a:xfrm><a:off x="0" y="0"/><a:ext cx="0" cy="0"/><a:chOff x="0" y="0"/><a:chExt cx="0" cy="0"/></a:xfrm></p:grpSpPr><p:sp><p:nvSpPr><p:cNvPr id="3" name="Title"/><p:cNvSpPr txBox="1"/><p:nvPr/></p:nvSpPr><p:spPr><a:xfrm><a:off x="762000" y="457200"/><a:ext cx="16764000" cy="634789"/></a:xfrm><a:prstGeom prst="rect"><a:avLst/></a:prstGeom><a:noFill/><a:ln><a:noFill/></a:ln></p:spPr><p:txBody><a:bodyPr wrap="square" lIns="0" tIns="0" rIns="0" bIns="0" rtlCol="0" anchor="t"><a:spAutoFit/></a:bodyPr><a:lstStyle/><a:p><a:pPr marL="0" indent="0" algn="l"><a:lnSpc><a:spcPts val="5000"/></a:lnSpc><a:spcBef><a:spcPct val="0"/></a:spcBef><a:buNone/></a:pPr><a:r><a:rPr lang="en-US" sz="4000" b="1" dirty="0"><a:solidFill><a:srgbClr val="1B2D4F"/></a:solidFill><a:latin typeface="Nunito Bold"/><a:ea typeface="Nunito Bold"/><a:cs typeface="Nunito Bold"/><a:sym typeface="Nunito Bold"/></a:rPr><a:t>SMEs have the Most to Gain from AI</a:t></a:r><a:endParaRPr lang="en-US" sz="1900" dirty="0"><a:solidFill><a:srgbClr val="7A9AAF"/></a:solidFill><a:latin typeface="Nunito"/><a:ea typeface="Nunito"/><a:cs typeface="Nunito"/><a:sym typeface="Nunito"/></a:endParaRPr></a:p></p:txBody></p:sp><p:sp><p:nvSpPr><p:cNvPr id="5" name="LHead"/><p:cNvSpPr txBox="1"/><p:nvPr/></p:nvSpPr><p:spPr><a:xfrm><a:off x="762000" y="1485900"/><a:ext cx="8200000" cy="500000"/></a:xfrm><a:prstGeom prst="rect"><a:avLst/></a:prstGeom><a:noFill/><a:ln><a:noFill/></a:ln></p:spPr><p:txBody><a:bodyPr wrap="square" lIns="0" tIns="0" rIns="0" bIns="0" rtlCol="0" anchor="ctr"><a:spAutoFit/></a:bodyPr><a:lstStyle/><a:p><a:pPr marL="0" indent="0" algn="l"><a:lnSpc><a:spcPts val="2700"/></a:lnSpc><a:spcBef><a:spcPct val="0"/></a:spcBef><a:buNone/></a:pPr><a:r><a:rPr lang="en-US" sz="2200" b="1" dirty="0"><a:solidFill><a:srgbClr val="1B2D4F"/></a:solidFill><a:latin typeface="Nunito Bold"/><a:ea typeface="Nunito Bold"/><a:cs typeface="Nunito Bold"/><a:sym typeface="Nunito Bold"/></a:rPr><a:t>Why SMEs Struggle More</a:t></a:r></a:p></p:txBody></p:sp><p:sp><p:nvSpPr><p:cNvPr id="10" name="BIc0"/><p:cNvSpPr/><p:nvPr/></p:nvSpPr><p:spPr><a:xfrm><a:off x="762000" y="2135900"/><a:ext cx="700000" cy="700000"/></a:xfrm><a:prstGeom prst="roundRect"><a:avLst><a:gd name="adj" fmla="val 50000"/></a:avLst></a:prstGeom><a:solidFill><a:srgbClr val="2BBFB0"/></a:solidFill><a:ln><a:noFill/></a:ln></p:spPr><p:txBody><a:bodyPr/><a:lstStyle/><a:p><a:endParaRPr lang="en-US"/></a:p></p:txBody></p:sp><p:sp><p:nvSpPr><p:cNvPr id="11" name="BIt0"/><p:cNvSpPr txBox="1"/><p:nvPr/></p:nvSpPr><p:spPr><a:xfrm><a:off x="762000" y="2135900"/><a:ext cx="700000" cy="700000"/></a:xfrm><a:prstGeom prst="rect"><a:avLst/></a:prstGeom><a:noFill/><a:ln><a:noFill/></a:ln></p:spPr><p:txBody><a:bodyPr wrap="square" lIns="0" tIns="0" rIns="0" bIns="0" rtlCol="0" anchor="ctr"><a:spAutoFit/></a:bodyPr><a:lstStyle/><a:p><a:pPr marL="0" indent="0" algn="ctr"><a:lnSpc><a:spcPts val="2400"/></a:lnSpc><a:spcBef><a:spcPct val="0"/></a:spcBef><a:buNone/></a:pPr><a:r><a:rPr lang="en-US" sz="2000" b="1" dirty="0"><a:solidFill><a:srgbClr val="1B2D4F"/></a:solidFill><a:latin typeface="Nunito Bold"/><a:ea typeface="Nunito Bold"/><a:cs typeface="Nunito Bold"/><a:sym typeface="Nunito Bold"/></a:rPr><a:t>D</a:t></a:r></a:p></p:txBody></p:sp><p:sp><p:nvSpPr><p:cNvPr id="12" name="BHd0"/><p:cNvSpPr txBox="1"/><p:nvPr/></p:nvSpPr><p:spPr><a:xfrm><a:off x="1562000" y="2135900"/><a:ext cx="7400000" cy="500000"/></a:xfrm><a:prstGeom prst="rect"><a:avLst/></a:prstGeom><a:noFill/><a:ln><a:noFill/></a:ln></p:spPr><p:txBody><a:bodyPr wrap="square" lIns="0" tIns="0" rIns="0" bIns="0" rtlCol="0" anchor="ctr"><a:spAutoFit/></a:bodyPr><a:lstStyle/><a:p><a:pPr marL="0" indent="0" algn="l"><a:lnSpc><a:spcPts val="2400"/></a:lnSpc><a:spcBef><a:spcPct val="0"/></a:spcBef><a:buNone/></a:pPr><a:r><a:rPr lang="en-US" sz="2000" b="1" dirty="0"><a:solidFill><a:srgbClr val="1B2D4F"/></a:solidFill><a:latin typeface="Nunito Bold"/><a:ea typeface="Nunito Bold"/><a:cs typeface="Nunito Bold"/><a:sym typeface="Nunito Bold"/></a:rPr><a:t>Fragmented Data</a:t></a:r></a:p></p:txBody></p:sp><p:sp><p:nvSpPr><p:cNvPr id="13" name="BDsc0"/><p:cNvSpPr txBox="1"/><p:nvPr/></p:nvSpPr><p:spPr><a:xfrm><a:off x="1562000" y="2615900"/><a:ext cx="7400000" cy="700000"/></a:xfrm><a:prstGeom prst="rect"><a:avLst/></a:prstGeom><a:noFill/><a:ln><a:noFill/></a:ln></p:spPr><p:txBody><a:bodyPr wrap="square" lIns="0" tIns="0" rIns="0" bIns="0" rtlCol="0" anchor="t"><a:spAutoFit/></a:bodyPr><a:lstStyle/><a:p><a:pPr marL="0" indent="0" algn="l"><a:lnSpc><a:spcPts val="1900"/></a:lnSpc><a:spcBef><a:spcPct val="0"/></a:spcBef><a:buNone/></a:pPr><a:r><a:rPr lang="en-US" sz="1500" dirty="0"><a:solidFill><a:srgbClr val="6B7280"/></a:solidFill><a:latin typeface="Nunito"/><a:ea typeface="Nunito"/><a:cs typeface="Nunito"/><a:sym typeface="Nunito"/></a:rPr><a:t>Information lives in spreadsheets, email threads and legacy systems — not integrated platforms.</a:t></a:r></a:p></p:txBody></p:sp><p:sp><p:nvSpPr><p:cNvPr id="14" name="BBg10"/><p:cNvSpPr/><p:nvPr/></p:nvSpPr><p:spPr><a:xfrm><a:off x="1562000" y="3335900"/><a:ext cx="7400000" cy="280000"/></a:xfrm><a:prstGeom prst="rect"><a:avLst/></a:prstGeom><a:solidFill><a:srgbClr val="E8F7F6"/></a:solidFill><a:ln><a:noFill/></a:ln></p:spPr><p:txBody><a:bodyPr/><a:lstStyle/><a:p><a:endParaRPr lang="en-US"/></a:p></p:txBody></p:sp><p:sp><p:nvSpPr><p:cNvPr id="15" name="BFl10"/><p:cNvSpPr/><p:nvPr/></p:nvSpPr><p:spPr><a:xfrm><a:off x="1562000" y="3335900"/><a:ext cx="4588000" cy="280000"/></a:xfrm><a:prstGeom prst="rect"><a:avLst/></a:prstGeom><a:solidFill><a:srgbClr val="2E5090"/></a:solidFill><a:ln><a:noFill/></a:ln></p:spPr><p:txBody><a:bodyPr/><a:lstStyle/><a:p><a:endParaRPr lang="en-US"/></a:p></p:txBody></p:sp><p:sp><p:nvSpPr><p:cNvPr id="16" name="BLb10"/><p:cNvSpPr txBox="1"/><p:nvPr/></p:nvSpPr><p:spPr><a:xfrm><a:off x="1562000" y="3335900"/><a:ext cx="4588000" cy="280000"/></a:xfrm><a:prstGeom prst="rect"><a:avLst/></a:prstGeom><a:noFill/><a:ln><a:noFill/></a:ln></p:spPr><p:txBody><a:bodyPr wrap="square" lIns="0" tIns="0" rIns="0" bIns="0" rtlCol="0" anchor="ctr"><a:spAutoFit/></a:bodyPr><a:lstStyle/><a:p><a:pPr marL="0" indent="0" algn="r"><a:lnSpc><a:spcPts val="1400"/></a:lnSpc><a:spcBef><a:spcPct val="0"/></a:spcBef><a:buNone/></a:pPr><a:r><a:rPr lang="en-US" sz="1100" b="1" dirty="0"><a:solidFill><a:srgbClr val="FFFFFF"/></a:solidFill><a:latin typeface="Nunito Bold"/><a:ea typeface="Nunito Bold"/><a:cs typeface="Nunito Bold"/><a:sym typeface="Nunito Bold"/></a:rPr><a:t>Large Enterprise  62%</a:t></a:r></a:p></p:txBody></p:sp><p:sp><p:nvSpPr><p:cNvPr id="17" name="BBg20"/><p:cNvSpPr/><p:nvPr/></p:nvSpPr><p:spPr><a:xfrm><a:off x="1562000" y="3675900"/><a:ext cx="7400000" cy="280000"/></a:xfrm><a:prstGeom prst="rect"><a:avLst/></a:prstGeom><a:solidFill><a:srgbClr val="E8F7F6"/></a:solidFill><a:ln><a:noFill/></a:ln></p:spPr><p:txBody><a:bodyPr/><a:lstStyle/><a:p><a:endParaRPr lang="en-US"/></a:p></p:txBody></p:sp><p:sp><p:nvSpPr><p:cNvPr id="18" name="BFl20"/><p:cNvSpPr/><p:nvPr/></p:nvSpPr><p:spPr><a:xfrm><a:off x="1562000" y="3675900"/><a:ext cx="1036000" cy="280000"/></a:xfrm><a:prstGeom prst="rect"><a:avLst/></a:prstGeom><a:solidFill><a:srgbClr val="2BBFB0"/></a:solidFill><a:ln><a:noFill/></a:ln></p:spPr><p:txBody><a:bodyPr/><a:lstStyle/><a:p><a:endParaRPr lang="en-US"/></a:p></p:txBody></p:sp><p:sp><p:nvSpPr><p:cNvPr id="19" name="BLb20"/><p:cNvSpPr txBox="1"/><p:nvPr/></p:nvSpPr><p:spPr><a:xfrm><a:off x="1562000" y="3675900"/><a:ext cx="1736000" cy="280000"/></a:xfrm><a:prstGeom prst="rect"><a:avLst/></a:prstGeom><a:noFill/><a:ln><a:noFill/></a:ln></p:spPr><p:txBody><a:bodyPr wrap="square" lIns="0" tIns="0" rIns="0" bIns="0" rtlCol="0" anchor="ctr"><a:spAutoFit/></a:bodyPr><a:lstStyle/><a:p><a:pPr marL="0" indent="0" algn="r"><a:lnSpc><a:spcPts val="1400"/></a:lnSpc><a:spcBef><a:spcPct val="0"/></a:spcBef><a:buNone/></a:pPr><a:r><a:rPr lang="en-US" sz="1100" b="1" dirty="0"><a:solidFill><a:srgbClr val="1B2D4F"/></a:solidFill><a:latin typeface="Nunito Bold"/><a:ea typeface="Nunito Bold"/><a:cs typeface="Nunito Bold"/><a:sym typeface="Nunito Bold"/></a:rPr><a:t>SME  14%</a:t></a:r></a:p></p:txBody></p:sp><p:sp><p:nvSpPr><p:cNvPr id="30" name="BIc1"/><p:cNvSpPr/><p:nvPr/></p:nvSpPr><p:spPr><a:xfrm><a:off x="762000" y="4535900"/><a:ext cx="700000" cy="700000"/></a:xfrm><a:prstGeom prst="roundRect"><a:avLst><a:gd name="adj" fmla="val 50000"/></a:avLst></a:prstGeom><a:solidFill><a:srgbClr val="2BBFB0"/></a:solidFill><a:ln><a:noFill/></a:ln></p:spPr><p:txBody><a:bodyPr/><a:lstStyle/><a:p><a:endParaRPr lang="en-US"/></a:p></p:txBody></p:sp><p:sp><p:nvSpPr><p:cNvPr id="31" name="BIt1"/><p:cNvSpPr txBox="1"/><p:nvPr/></p:nvSpPr><p:spPr><a:xfrm><a:off x="762000" y="4535900"/><a:ext cx="700000" cy="700000"/></a:xfrm><a:prstGeom prst="rect"><a:avLst/></a:prstGeom><a:noFill/><a:ln><a:noFill/></a:ln></p:spPr><p:txBody><a:bodyPr wrap="square" lIns="0" tIns="0" rIns="0" bIns="0" rtlCol="0" anchor="ctr"><a:spAutoFit/></a:bodyPr><a:lstStyle/><a:p><a:pPr marL="0" indent="0" algn="ctr"><a:lnSpc><a:spcPts val="2400"/></a:lnSpc><a:spcBef><a:spcPct val="0"/></a:spcBef><a:buNone/></a:pPr><a:r><a:rPr lang="en-US" sz="2000" b="1" dirty="0"><a:solidFill><a:srgbClr val="1B2D4F"/></a:solidFill><a:latin typeface="Nunito Bold"/><a:ea typeface="Nunito Bold"/><a:cs typeface="Nunito Bold"/><a:sym typeface="Nunito Bold"/></a:rPr><a:t>IT</a:t></a:r></a:p></p:txBody></p:sp><p:sp><p:nvSpPr><p:cNvPr id="32" name="BHd1"/><p:cNvSpPr txBox="1"/><p:nvPr/></p:nvSpPr><p:spPr><a:xfrm><a:off x="1562000" y="4535900"/><a:ext cx="7400000" cy="500000"/></a:xfrm><a:prstGeom prst="rect"><a:avLst/></a:prstGeom><a:noFill/><a:ln><a:noFill/></a:ln></p:spPr><p:txBody><a:bodyPr wrap="square" lIns="0" tIns="0" rIns="0" bIns="0" rtlCol="0" anchor="ctr"><a:spAutoFit/></a:bodyPr><a:lstStyle/><a:p><a:pPr marL="0" indent="0" algn="l"><a:lnSpc><a:spcPts val="2400"/></a:lnSpc><a:spcBef><a:spcPct val="0"/></a:spcBef><a:buNone/></a:pPr><a:r><a:rPr lang="en-US" sz="2000" b="1" dirty="0"><a:solidFill><a:srgbClr val="1B2D4F"/></a:solidFill><a:latin typeface="Nunito Bold"/><a:ea typeface="Nunito Bold"/><a:cs typeface="Nunito Bold"/><a:sym typeface="Nunito Bold"/></a:rPr><a:t>No Dedicated IT / AI Team</a:t></a:r></a:p></p:txBody></p:sp><p:sp><p:nvSpPr><p:cNvPr id="33" name="BDsc1"/><p:cNvSpPr txBox="1"/><p:nvPr/></p:nvSpPr><p:spPr><a:xfrm><a:off x="1562000" y="5015900"/><a:ext cx="7400000" cy="700000"/></a:xfrm><a:prstGeom prst="rect"><a:avLst/></a:prstGeom><a:noFill/><a:ln><a:noFill/></a:ln></p:spPr><p:txBody><a:bodyPr wrap="square" lIns="0" tIns="0" rIns="0" bIns="0" rtlCol="0" anchor="t"><a:spAutoFit/></a:bodyPr><a:lstStyle/><a:p><a:pPr marL="0" indent="0" algn="l"><a:lnSpc><a:spcPts val="1900"/></a:lnSpc><a:spcBef><a:spcPct val="0"/></a:spcBef><a:buNone/></a:pPr><a:r><a:rPr lang="en-US" sz="1500" dirty="0"><a:solidFill><a:srgbClr val="6B7280"/></a:solidFill><a:latin typeface="Nunito"/><a:ea typeface="Nunito"/><a:cs typeface="Nunito"/><a:sym typeface="Nunito"/></a:rPr><a:t>Large enterprises have dedicated AI teams. SMEs must figure out integration entirely on their own.</a:t></a:r></a:p></p:txBody></p:sp><p:sp><p:nvSpPr><p:cNvPr id="34" name="BBg11"/><p:cNvSpPr/><p:nvPr/></p:nvSpPr><p:spPr><a:xfrm><a:off x="1562000" y="5735900"/><a:ext cx="7400000" cy="280000"/></a:xfrm><a:prstGeom prst="rect"><a:avLst/></a:prstGeom><a:solidFill><a:srgbClr val="E8F7F6"/></a:solidFill><a:ln><a:noFill/></a:ln></p:spPr><p:txBody><a:bodyPr/><a:lstStyle/><a:p><a:endParaRPr lang="en-US"/></a:p></p:txBody></p:sp><p:sp><p:nvSpPr><p:cNvPr id="35" name="BFl11"/><p:cNvSpPr/><p:nvPr/></p:nvSpPr><p:spPr><a:xfrm><a:off x="1562000" y="5735900"/><a:ext cx="5254000" cy="280000"/></a:xfrm><a:prstGeom prst="rect"><a:avLst/></a:prstGeom><a:solidFill><a:srgbClr val="2E5090"/></a:solidFill><a:ln><a:noFill/></a:ln></p:spPr><p:txBody><a:bodyPr/><a:lstStyle/><a:p><a:endParaRPr lang="en-US"/></a:p></p:txBody></p:sp><p:sp><p:nvSpPr><p:cNvPr id="36" name="BLb11"/><p:cNvSpPr txBox="1"/><p:nvPr/></p:nvSpPr><p:spPr><a:xfrm><a:off x="1562000" y="5735900"/><a:ext cx="5254000" cy="280000"/></a:xfrm><a:prstGeom prst="rect"><a:avLst/></a:prstGeom><a:noFill/><a:ln><a:noFill/></a:ln></p:spPr><p:txBody><a:bodyPr wrap="square" lIns="0" tIns="0" rIns="0" bIns="0" rtlCol="0" anchor="ctr"><a:spAutoFit/></a:bodyPr><a:lstStyle/><a:p><a:pPr marL="0" indent="0" algn="r"><a:lnSpc><a:spcPts val="1400"/></a:lnSpc><a:spcBef><a:spcPct val="0"/></a:spcBef><a:buNone/></a:pPr><a:r><a:rPr lang="en-US" sz="1100" b="1" dirty="0"><a:solidFill><a:srgbClr val="FFFFFF"/></a:solidFill><a:latin typeface="Nunito Bold"/><a:ea typeface="Nunito Bold"/><a:cs typeface="Nunito Bold"/><a:sym typeface="Nunito Bold"/></a:rPr><a:t>Large Enterprise  71%</a:t></a:r></a:p></p:txBody></p:sp><p:sp><p:nvSpPr><p:cNvPr id="37" name="BBg21"/><p:cNvSpPr/><p:nvPr/></p:nvSpPr><p:spPr><a:xfrm><a:off x="1562000" y="6075900"/><a:ext cx="7400000" cy="280000"/></a:xfrm><a:prstGeom prst="rect"><a:avLst/></a:prstGeom><a:solidFill><a:srgbClr val="E8F7F6"/></a:solidFill><a:ln><a:noFill/></a:ln></p:spPr><p:txBody><a:bodyPr/><a:lstStyle/><a:p><a:endParaRPr lang="en-US"/></a:p></p:txBody></p:sp><p:sp><p:nvSpPr><p:cNvPr id="38" name="BFl21"/><p:cNvSpPr/><p:nvPr/></p:nvSpPr><p:spPr><a:xfrm><a:off x="1562000" y="6075900"/><a:ext cx="1332000" cy="280000"/></a:xfrm><a:prstGeom prst="rect"><a:avLst/></a:prstGeom><a:solidFill><a:srgbClr val="2BBFB0"/></a:solidFill><a:ln><a:noFill/></a:ln></p:spPr><p:txBody><a:bodyPr/><a:lstStyle/><a:p><a:endParaRPr lang="en-US"/></a:p></p:txBody></p:sp><p:sp><p:nvSpPr><p:cNvPr id="39" name="BLb21"/><p:cNvSpPr txBox="1"/><p:nvPr/></p:nvSpPr><p:spPr><a:xfrm><a:off x="1562000" y="6075900"/><a:ext cx="2032000" cy="280000"/></a:xfrm><a:prstGeom prst="rect"><a:avLst/></a:prstGeom><a:noFill/><a:ln><a:noFill/></a:ln></p:spPr><p:txBody><a:bodyPr wrap="square" lIns="0" tIns="0" rIns="0" bIns="0" rtlCol="0" anchor="ctr"><a:spAutoFit/></a:bodyPr><a:lstStyle/><a:p><a:pPr marL="0" indent="0" algn="r"><a:lnSpc><a:spcPts val="1400"/></a:lnSpc><a:spcBef><a:spcPct val="0"/></a:spcBef><a:buNone/></a:pPr><a:r><a:rPr lang="en-US" sz="1100" b="1" dirty="0"><a:solidFill><a:srgbClr val="1B2D4F"/></a:solidFill><a:latin typeface="Nunito Bold"/><a:ea typeface="Nunito Bold"/><a:cs typeface="Nunito Bold"/><a:sym typeface="Nunito Bold"/></a:rPr><a:t>SME  18%</a:t></a:r></a:p></p:txBody></p:sp><p:sp><p:nvSpPr><p:cNvPr id="50" name="BIc2"/><p:cNvSpPr/><p:nvPr/></p:nvSpPr><p:spPr><a:xfrm><a:off x="762000" y="6935900"/><a:ext cx="700000" cy="700000"/></a:xfrm><a:prstGeom prst="roundRect"><a:avLst><a:gd name="adj" fmla="val 50000"/></a:avLst></a:prstGeom><a:solidFill><a:srgbClr val="2BBFB0"/></a:solidFill><a:ln><a:noFill/></a:ln></p:spPr><p:txBody><a:bodyPr/><a:lstStyle/><a:p><a:endParaRPr lang="en-US"/></a:p></p:txBody></p:sp><p:sp><p:nvSpPr><p:cNvPr id="51" name="BIt2"/><p:cNvSpPr txBox="1"/><p:nvPr/></p:nvSpPr><p:spPr><a:xfrm><a:off x="762000" y="6935900"/><a:ext cx="700000" cy="700000"/></a:xfrm><a:prstGeom prst="rect"><a:avLst/></a:prstGeom><a:noFill/><a:ln><a:noFill/></a:ln></p:spPr><p:txBody><a:bodyPr wrap="square" lIns="0" tIns="0" rIns="0" bIns="0" rtlCol="0" anchor="ctr"><a:spAutoFit/></a:bodyPr><a:lstStyle/><a:p><a:pPr marL="0" indent="0" algn="ctr"><a:lnSpc><a:spcPts val="2400"/></a:lnSpc><a:spcBef><a:spcPct val="0"/></a:spcBef><a:buNone/></a:pPr><a:r><a:rPr lang="en-US" sz="2000" b="1" dirty="0"><a:solidFill><a:srgbClr val="1B2D4F"/></a:solidFill><a:latin typeface="Nunito Bold"/><a:ea typeface="Nunito Bold"/><a:cs typeface="Nunito Bold"/><a:sym typeface="Nunito Bold"/></a:rPr><a:t>$</a:t></a:r></a:p></p:txBody></p:sp><p:sp><p:nvSpPr><p:cNvPr id="52" name="BHd2"/><p:cNvSpPr txBox="1"/><p:nvPr/></p:nvSpPr><p:spPr><a:xfrm><a:off x="1562000" y="6935900"/><a:ext cx="7400000" cy="500000"/></a:xfrm><a:prstGeom prst="rect"><a:avLst/></a:prstGeom><a:noFill/><a:ln><a:noFill/></a:ln></p:spPr><p:txBody><a:bodyPr wrap="square" lIns="0" tIns="0" rIns="0" bIns="0" rtlCol="0" anchor="ctr"><a:spAutoFit/></a:bodyPr><a:lstStyle/><a:p><a:pPr marL="0" indent="0" algn="l"><a:lnSpc><a:spcPts val="2400"/></a:lnSpc><a:spcBef><a:spcPct val="0"/></a:spcBef><a:buNone/></a:pPr><a:r><a:rPr lang="en-US" sz="2000" b="1" dirty="0"><a:solidFill><a:srgbClr val="1B2D4F"/></a:solidFill><a:latin typeface="Nunito Bold"/><a:ea typeface="Nunito Bold"/><a:cs typeface="Nunito Bold"/><a:sym typeface="Nunito Bold"/></a:rPr><a:t>Budget Constraints</a:t></a:r></a:p></p:txBody></p:sp><p:sp><p:nvSpPr><p:cNvPr id="53" name="BDsc2"/><p:cNvSpPr txBox="1"/><p:nvPr/></p:nvSpPr><p:spPr><a:xfrm><a:off x="1562000" y="7415900"/><a:ext cx="7400000" cy="700000"/></a:xfrm><a:prstGeom prst="rect"><a:avLst/></a:prstGeom><a:noFill/><a:ln><a:noFill/></a:ln></p:spPr><p:txBody><a:bodyPr wrap="square" lIns="0" tIns="0" rIns="0" bIns="0" rtlCol="0" anchor="t"><a:spAutoFit/></a:bodyPr><a:lstStyle/><a:p><a:pPr marL="0" indent="0" algn="l"><a:lnSpc><a:spcPts val="1900"/></a:lnSpc><a:spcBef><a:spcPct val="0"/></a:spcBef><a:buNone/></a:pPr><a:r><a:rPr lang="en-US" sz="1500" dirty="0"><a:solidFill><a:srgbClr val="6B7280"/></a:solidFill><a:latin typeface="Nunito"/><a:ea typeface="Nunito"/><a:cs typeface="Nunito"/><a:sym typeface="Nunito"/></a:rPr><a:t>Enterprise AI tools require infrastructure investment, training and governance that most SMEs cannot absorb upfront.</a:t></a:r></a:p></p:txBody></p:sp><p:sp><p:nvSpPr><p:cNvPr id="54" name="BBg12"/><p:cNvSpPr/><p:nvPr/></p:nvSpPr><p:spPr><a:xfrm><a:off x="1562000" y="8135900"/><a:ext cx="7400000" cy="280000"/></a:xfrm><a:prstGeom prst="rect"><a:avLst/></a:prstGeom><a:solidFill><a:srgbClr val="E8F7F6"/></a:solidFill><a:ln><a:noFill/></a:ln></p:spPr><p:txBody><a:bodyPr/><a:lstStyle/><a:p><a:endParaRPr lang="en-US"/></a:p></p:txBody></p:sp><p:sp><p:nvSpPr><p:cNvPr id="55" name="BFl12"/><p:cNvSpPr/><p:nvPr/></p:nvSpPr><p:spPr><a:xfrm><a:off x="1562000" y="8135900"/><a:ext cx="4070000" cy="280000"/></a:xfrm><a:prstGeom prst="rect"><a:avLst/></a:prstGeom><a:solidFill><a:srgbClr val="2E5090"/></a:solidFill><a:ln><a:noFill/></a:ln></p:spPr><p:txBody><a:bodyPr/><a:lstStyle/><a:p><a:endParaRPr lang="en-US"/></a:p></p:txBody></p:sp><p:sp><p:nvSpPr><p:cNvPr id="56" name="BLb12"/><p:cNvSpPr txBox="1"/><p:nvPr/></p:nvSpPr><p:spPr><a:xfrm><a:off x="1562000" y="8135900"/><a:ext cx="4070000" cy="280000"/></a:xfrm><a:prstGeom prst="rect"><a:avLst/></a:prstGeom><a:noFill/><a:ln><a:noFill/></a:ln></p:spPr><p:txBody><a:bodyPr wrap="square" lIns="0" tIns="0" rIns="0" bIns="0" rtlCol="0" anchor="ctr"><a:spAutoFit/></a:bodyPr><a:lstStyle/><a:p><a:pPr marL="0" indent="0" algn="r"><a:lnSpc><a:spcPts val="1400"/></a:lnSpc><a:spcBef><a:spcPct val="0"/></a:spcBef><a:buNone/></a:pPr><a:r><a:rPr lang="en-US" sz="1100" b="1" dirty="0"><a:solidFill><a:srgbClr val="FFFFFF"/></a:solidFill><a:latin typeface="Nunito Bold"/><a:ea typeface="Nunito Bold"/><a:cs typeface="Nunito Bold"/><a:sym typeface="Nunito Bold"/></a:rPr><a:t>Large Enterprise  55%</a:t></a:r></a:p></p:txBody></p:sp><p:sp><p:nvSpPr><p:cNvPr id="57" name="BBg22"/><p:cNvSpPr/><p:nvPr/></p:nvSpPr><p:spPr><a:xfrm><a:off x="1562000" y="8475900"/><a:ext cx="7400000" cy="280000"/></a:xfrm><a:prstGeom prst="rect"><a:avLst/></a:prstGeom><a:solidFill><a:srgbClr val="E8F7F6"/></a:solidFill><a:ln><a:noFill/></a:ln></p:spPr><p:txBody><a:bodyPr/><a:lstStyle/><a:p><a:endParaRPr lang="en-US"/></a:p></p:txBody></p:sp><p:sp><p:nvSpPr><p:cNvPr id="58" name="BFl22"/><p:cNvSpPr/><p:nvPr/></p:nvSpPr><p:spPr><a:xfrm><a:off x="1562000" y="8475900"/><a:ext cx="888000" cy="280000"/></a:xfrm><a:prstGeom prst="rect"><a:avLst/></a:prstGeom><a:solidFill><a:srgbClr val="2BBFB0"/></a:solidFill><a:ln><a:noFill/></a:ln></p:spPr><p:txBody><a:bodyPr/><a:lstStyle/><a:p><a:endParaRPr lang="en-US"/></a:p></p:txBody></p:sp><p:sp><p:nvSpPr><p:cNvPr id="59" name="BLb22"/><p:cNvSpPr txBox="1"/><p:nvPr/></p:nvSpPr><p:spPr><a:xfrm><a:off x="1562000" y="8475900"/><a:ext cx="1588000" cy="280000"/></a:xfrm><a:prstGeom prst="rect"><a:avLst/></a:prstGeom><a:noFill/><a:ln><a:noFill/></a:ln></p:spPr><p:txBody><a:bodyPr wrap="square" lIns="0" tIns="0" rIns="0" bIns="0" rtlCol="0" anchor="ctr"><a:spAutoFit/></a:bodyPr><a:lstStyle/><a:p><a:pPr marL="0" indent="0" algn="r"><a:lnSpc><a:spcPts val="1400"/></a:lnSpc><a:spcBef><a:spcPct val="0"/></a:spcBef><a:buNone/></a:pPr><a:r><a:rPr lang="en-US" sz="1100" b="1" dirty="0"><a:solidFill><a:srgbClr val="1B2D4F"/></a:solidFill><a:latin typeface="Nunito Bold"/><a:ea typeface="Nunito Bold"/><a:cs typeface="Nunito Bold"/><a:sym typeface="Nunito Bold"/></a:rPr><a:t>SME  12%</a:t></a:r></a:p></p:txBody></p:sp><p:sp><p:nvSpPr><p:cNvPr id="70" name="Div"/><p:cNvSpPr/><p:nvPr/></p:nvSpPr><p:spPr><a:xfrm><a:off x="9162000" y="1333500"/><a:ext cx="15000" cy="8200000"/></a:xfrm><a:prstGeom prst="rect"><a:avLst/></a:prstGeom><a:solidFill><a:srgbClr val="D1D5DB"/></a:solidFill><a:ln><a:noFill/></a:ln></p:spPr><p:txBody><a:bodyPr/><a:lstStyle/><a:p><a:endParaRPr lang="en-US"/></a:p></p:txBody></p:sp><p:sp><p:nvSpPr><p:cNvPr id="71" name="SolPnl"/><p:cNvSpPr/><p:nvPr/></p:nvSpPr><p:spPr><a:xfrm><a:off x="9562000" y="1333500"/><a:ext cx="7964000" cy="8200000"/></a:xfrm><a:prstGeom prst="roundRect"><a:avLst><a:gd name="adj" fmla="val 20000"/></a:avLst></a:prstGeom><a:solidFill><a:srgbClr val="1B2D4F"/></a:solidFill><a:ln><a:noFill/></a:ln></p:spPr><p:txBody><a:bodyPr/><a:lstStyle/><a:p><a:endParaRPr lang="en-US"/></a:p></p:txBody></p:sp><p:sp><p:nvSpPr><p:cNvPr id="72" name="SolHd"/><p:cNvSpPr txBox="1"/><p:nvPr/></p:nvSpPr><p:spPr><a:xfrm><a:off x="9862000" y="1610375"/><a:ext cx="7364000" cy="346249"/></a:xfrm><a:prstGeom prst="rect"><a:avLst/></a:prstGeom><a:noFill/><a:ln><a:noFill/></a:ln></p:spPr><p:txBody><a:bodyPr wrap="square" lIns="0" tIns="0" rIns="0" bIns="0" rtlCol="0" anchor="ctr"><a:spAutoFit/></a:bodyPr><a:lstStyle/><a:p><a:pPr marL="0" indent="0" algn="ctr"><a:lnSpc><a:spcPts val="2700"/></a:lnSpc><a:spcBef><a:spcPct val="0"/></a:spcBef><a:buNone/></a:pPr><a:r><a:rPr lang="en-US" sz="2200" b="1" dirty="0"><a:solidFill><a:srgbClr val="2BBFB0"/></a:solidFill><a:latin typeface="Nunito Bold"/><a:ea typeface="Nunito Bold"/><a:cs typeface="Nunito Bold"/><a:sym typeface="Nunito Bold"/></a:rPr><a:t>How coaxis.ai Closes the Gap</a:t></a:r></a:p></p:txBody></p:sp><p:sp><p:nvSpPr><p:cNvPr id="80" name="SolBx0"/><p:cNvSpPr/><p:nvPr/></p:nvSpPr><p:spPr><a:xfrm><a:off x="9862000" y="2233500"/><a:ext cx="7364000" cy="1800000"/></a:xfrm><a:prstGeom prst="roundRect"><a:avLst><a:gd name="adj" fmla="val 14000"/></a:avLst></a:prstGeom><a:solidFill><a:srgbClr val="253E60"/></a:solidFill><a:ln><a:noFill/></a:ln></p:spPr><p:txBody><a:bodyPr/><a:lstStyle/><a:p><a:endParaRPr lang="en-US"/></a:p></p:txBody></p:sp><p:sp><p:nvSpPr><p:cNvPr id="81" name="SolH0"/><p:cNvSpPr txBox="1"/><p:nvPr/></p:nvSpPr><p:spPr><a:xfrm><a:off x="10062000" y="2383500"/><a:ext cx="6964000" cy="600000"/></a:xfrm><a:prstGeom prst="rect"><a:avLst/></a:prstGeom><a:noFill/><a:ln><a:noFill/></a:ln></p:spPr><p:txBody><a:bodyPr wrap="square" lIns="0" tIns="0" rIns="0" bIns="0" rtlCol="0" anchor="t"><a:spAutoFit/></a:bodyPr><a:lstStyle/><a:p><a:pPr marL="0" indent="0" algn="l"><a:lnSpc><a:spcPts val="2200"/></a:lnSpc><a:spcBef><a:spcPct val="0"/></a:spcBef><a:buNone/></a:pPr><a:r><a:rPr lang="en-US" sz="1800" b="1" dirty="0"><a:solidFill><a:srgbClr val="2BBFB0"/></a:solidFill><a:latin typeface="Nunito Bold"/><a:ea typeface="Nunito Bold"/><a:cs typeface="Nunito Bold"/><a:sym typeface="Nunito Bold"/></a:rPr><a:t>✓  Data Readiness First</a:t></a:r></a:p></p:txBody></p:sp><p:sp><p:nvSpPr><p:cNvPr id="82" name="SolB0"/><p:cNvSpPr txBox="1"/><p:nvPr/></p:nvSpPr><p:spPr><a:xfrm><a:off x="10062000" y="2913500"/><a:ext cx="6964000" cy="1000000"/></a:xfrm><a:prstGeom prst="rect"><a:avLst/></a:prstGeom><a:noFill/><a:ln><a:noFill/></a:ln></p:spPr><p:txBody><a:bodyPr wrap="square" lIns="0" tIns="0" rIns="0" bIns="0" rtlCol="0" anchor="t"><a:spAutoFit/></a:bodyPr><a:lstStyle/><a:p><a:pPr marL="0" indent="0" algn="l"><a:lnSpc><a:spcPts val="1900"/></a:lnSpc><a:spcBef><a:spcPct val="0"/></a:spcBef><a:buNone/></a:pPr><a:r><a:rPr lang="en-US" sz="1500" dirty="0"><a:solidFill><a:srgbClr val="D1D5DB"/></a:solidFill><a:latin typeface="Nunito"/><a:ea typeface="Nunito"/><a:cs typeface="Nunito"/><a:sym typeface="Nunito"/></a:rPr><a:t>We assess and prepare your data so AI can actually use it — spreadsheets, PDFs, legacy systems all included.</a:t></a:r></a:p></p:txBody></p:sp><p:sp><p:nvSpPr><p:cNvPr id="85" name="SolBx1"/><p:cNvSpPr/><p:nvPr/></p:nvSpPr><p:spPr><a:xfrm><a:off x="9862000" y="4153500"/><a:ext cx="7364000" cy="1800000"/></a:xfrm><a:prstGeom prst="roundRect"><a:avLst><a:gd name="adj" fmla="val 14000"/></a:avLst></a:prstGeom><a:solidFill><a:srgbClr val="253E60"/></a:solidFill><a:ln><a:noFill/></a:ln></p:spPr><p:txBody><a:bodyPr/><a:lstStyle/><a:p><a:endParaRPr lang="en-US"/></a:p></p:txBody></p:sp><p:sp><p:nvSpPr><p:cNvPr id="86" name="SolH1"/><p:cNvSpPr txBox="1"/><p:nvPr/></p:nvSpPr><p:spPr><a:xfrm><a:off x="10062000" y="4303500"/><a:ext cx="6964000" cy="600000"/></a:xfrm><a:prstGeom prst="rect"><a:avLst/></a:prstGeom><a:noFill/><a:ln><a:noFill/></a:ln></p:spPr><p:txBody><a:bodyPr wrap="square" lIns="0" tIns="0" rIns="0" bIns="0" rtlCol="0" anchor="t"><a:spAutoFit/></a:bodyPr><a:lstStyle/><a:p><a:pPr marL="0" indent="0" algn="l"><a:lnSpc><a:spcPts val="2200"/></a:lnSpc><a:spcBef><a:spcPct val="0"/></a:spcBef><a:buNone/></a:pPr><a:r><a:rPr lang="en-US" sz="1800" b="1" dirty="0"><a:solidFill><a:srgbClr val="2BBFB0"/></a:solidFill><a:latin typeface="Nunito Bold"/><a:ea typeface="Nunito Bold"/><a:cs typeface="Nunito Bold"/><a:sym typeface="Nunito Bold"/></a:rPr><a:t>✓  No AI team needed</a:t></a:r></a:p></p:txBody></p:sp><p:sp><p:nvSpPr><p:cNvPr id="87" name="SolB1"/><p:cNvSpPr txBox="1"/><p:nvPr/></p:nvSpPr><p:spPr><a:xfrm><a:off x="10062000" y="4833500"/><a:ext cx="6964000" cy="1000000"/></a:xfrm><a:prstGeom prst="rect"><a:avLst/></a:prstGeom><a:noFill/><a:ln><a:noFill/></a:ln></p:spPr><p:txBody><a:bodyPr wrap="square" lIns="0" tIns="0" rIns="0" bIns="0" rtlCol="0" anchor="t"><a:spAutoFit/></a:bodyPr><a:lstStyle/><a:p><a:pPr marL="0" indent="0" algn="l"><a:lnSpc><a:spcPts val="1900"/></a:lnSpc><a:spcBef><a:spcPct val="0"/></a:spcBef><a:buNone/></a:pPr><a:r><a:rPr lang="en-US" sz="1500" dirty="0"><a:solidFill><a:srgbClr val="D1D5DB"/></a:solidFill><a:latin typeface="Nunito"/><a:ea typeface="Nunito"/><a:cs typeface="Nunito"/><a:sym typeface="Nunito"/></a:rPr><a:t>Our team is your AI team. We bring engineers, architects and domain experts you do not have yet.</a:t></a:r></a:p></p:txBody></p:sp><p:sp><p:nvSpPr><p:cNvPr id="90" name="SolBx2"/><p:cNvSpPr/><p:nvPr/></p:nvSpPr><p:spPr><a:xfrm><a:off x="9862000" y="6073500"/><a:ext cx="7364000" cy="1800000"/></a:xfrm><a:prstGeom prst="roundRect"><a:avLst><a:gd name="adj" fmla="val 14000"/></a:avLst></a:prstGeom><a:solidFill><a:srgbClr val="253E60"/></a:solidFill><a:ln><a:noFill/></a:ln></p:spPr><p:txBody><a:bodyPr/><a:lstStyle/><a:p><a:endParaRPr lang="en-US"/></a:p></p:txBody></p:sp><p:sp><p:nvSpPr><p:cNvPr id="91" name="SolH2"/><p:cNvSpPr txBox="1"/><p:nvPr/></p:nvSpPr><p:spPr><a:xfrm><a:off x="10062000" y="6223500"/><a:ext cx="6964000" cy="600000"/></a:xfrm><a:prstGeom prst="rect"><a:avLst/></a:prstGeom><a:noFill/><a:ln><a:noFill/></a:ln></p:spPr><p:txBody><a:bodyPr wrap="square" lIns="0" tIns="0" rIns="0" bIns="0" rtlCol="0" anchor="t"><a:spAutoFit/></a:bodyPr><a:lstStyle/><a:p><a:pPr marL="0" indent="0" algn="l"><a:lnSpc><a:spcPts val="2200"/></a:lnSpc><a:spcBef><a:spcPct val="0"/></a:spcBef><a:buNone/></a:pPr><a:r><a:rPr lang="en-US" sz="1800" b="1" dirty="0"><a:solidFill><a:srgbClr val="2BBFB0"/></a:solidFill><a:latin typeface="Nunito Bold"/><a:ea typeface="Nunito Bold"/><a:cs typeface="Nunito Bold"/><a:sym typeface="Nunito Bold"/></a:rPr><a:t>✓  Fixed-fee, phased entry</a:t></a:r></a:p></p:txBody></p:sp><p:sp><p:nvSpPr><p:cNvPr id="92" name="SolB2"/><p:cNvSpPr txBox="1"/><p:nvPr/></p:nvSpPr><p:spPr><a:xfrm><a:off x="10062000" y="6753500"/><a:ext cx="6964000" cy="1000000"/></a:xfrm><a:prstGeom prst="rect"><a:avLst/></a:prstGeom><a:noFill/><a:ln><a:noFill/></a:ln></p:spPr><p:txBody><a:bodyPr wrap="square" lIns="0" tIns="0" rIns="0" bIns="0" rtlCol="0" anchor="t"><a:spAutoFit/></a:bodyPr><a:lstStyle/><a:p><a:pPr marL="0" indent="0" algn="l"><a:lnSpc><a:spcPts val="1900"/></a:lnSpc><a:spcBef><a:spcPct val="0"/></a:spcBef><a:buNone/></a:pPr><a:r><a:rPr lang="en-US" sz="1500" dirty="0"><a:solidFill><a:srgbClr val="D1D5DB"/></a:solidFill><a:latin typeface="Nunito"/><a:ea typeface="Nunito"/><a:cs typeface="Nunito"/><a:sym typeface="Nunito"/></a:rPr><a:t>Start with a 4-6 week diagnostic. No open-ended commitments, no surprise costs, clear deliverables.</a:t></a:r></a:p></p:txBody></p:sp><p:sp><p:nvSpPr><p:cNvPr id="95" name="SolBx3"/><p:cNvSpPr/><p:nvPr/></p:nvSpPr><p:spPr><a:xfrm><a:off x="9862000" y="7993500"/><a:ext cx="7364000" cy="1800000"/></a:xfrm><a:prstGeom prst="roundRect"><a:avLst><a:gd name="adj" fmla="val 14000"/></a:avLst></a:prstGeom><a:solidFill><a:srgbClr val="253E60"/></a:solidFill><a:ln><a:noFill/></a:ln></p:spPr><p:txBody><a:bodyPr/><a:lstStyle/><a:p><a:endParaRPr lang="en-US"/></a:p></p:txBody></p:sp><p:sp><p:nvSpPr><p:cNvPr id="96" name="SolH3"/><p:cNvSpPr txBox="1"/><p:nvPr/></p:nvSpPr><p:spPr><a:xfrm><a:off x="10062000" y="8143500"/><a:ext cx="6964000" cy="600000"/></a:xfrm><a:prstGeom prst="rect"><a:avLst/></a:prstGeom><a:noFill/><a:ln><a:noFill/></a:ln></p:spPr><p:txBody><a:bodyPr wrap="square" lIns="0" tIns="0" rIns="0" bIns="0" rtlCol="0" anchor="t"><a:spAutoFit/></a:bodyPr><a:lstStyle/><a:p><a:pPr marL="0" indent="0" algn="l"><a:lnSpc><a:spcPts val="2200"/></a:lnSpc><a:spcBef><a:spcPct val="0"/></a:spcBef><a:buNone/></a:pPr><a:r><a:rPr lang="en-US" sz="1800" b="1" dirty="0"><a:solidFill><a:srgbClr val="2BBFB0"/></a:solidFill><a:latin typeface="Nunito Bold"/><a:ea typeface="Nunito Bold"/><a:cs typeface="Nunito Bold"/><a:sym typeface="Nunito Bold"/></a:rPr><a:t>✓  SME-sized governance</a:t></a:r></a:p></p:txBody></p:sp><p:sp><p:nvSpPr><p:cNvPr id="97" name="SolB3"/><p:cNvSpPr txBox="1"/><p:nvPr/></p:nvSpPr><p:spPr><a:xfrm><a:off x="10062000" y="8673500"/><a:ext cx="6964000" cy="1000000"/></a:xfrm><a:prstGeom prst="rect"><a:avLst/></a:prstGeom><a:noFill/><a:ln><a:noFill/></a:ln></p:spPr><p:txBody><a:bodyPr wrap="square" lIns="0" tIns="0" rIns="0" bIns="0" rtlCol="0" anchor="t"><a:spAutoFit/></a:bodyPr><a:lstStyle/><a:p><a:pPr marL="0" indent="0" algn="l"><a:lnSpc><a:spcPts val="1900"/></a:lnSpc><a:spcBef><a:spcPct val="0"/></a:spcBef><a:buNone/></a:pPr><a:r><a:rPr lang="en-US" sz="1500" dirty="0"><a:solidFill><a:srgbClr val="D1D5DB"/></a:solidFill><a:latin typeface="Nunito"/><a:ea typeface="Nunito"/><a:cs typeface="Nunito"/><a:sym typeface="Nunito"/></a:rPr><a:t>Right-sized security, compliance guardrails and human-in-the-loop — enterprise rigour without enterprise bloat.</a:t></a:r></a:p></p:txBody></p:sp><p:sp><p:nvSpPr><p:cNvPr id="99" name="Src"/><p:cNvSpPr txBox="1"/><p:nvPr/></p:nvSpPr><p:spPr><a:xfrm><a:off x="762000" y="9850000"/><a:ext cx="8200000" cy="380000"/></a:xfrm><a:prstGeom prst="rect"><a:avLst/></a:prstGeom><a:noFill/><a:ln><a:noFill/></a:ln></p:spPr><p:txBody><a:bodyPr wrap="square" lIns="0" tIns="0" rIns="0" bIns="0" rtlCol="0" anchor="t"><a:spAutoFit/></a:bodyPr><a:lstStyle/><a:p><a:pPr marL="0" indent="0" algn="l"><a:lnSpc><a:spcPts val="1400"/></a:lnSpc><a:spcBef><a:spcPct val="0"/></a:spcBef><a:buNone/></a:pPr><a:r><a:rPr lang="en-US" sz="1100" dirty="0"><a:solidFill><a:srgbClr val="9DB8C8"/></a:solidFill><a:latin typeface="Nunito"/><a:ea typeface="Nunito"/><a:cs typeface="Nunito"/><a:sym typeface="Nunito"/></a:rPr><a:t>Source: Singapore Digital Economy Report 2024 / IMDA   ·   Enterprise vs SME AI adoption rates</a:t></a:r></a:p></p:txBody></p:sp><p:sp><p:nvSpPr><p:cNvPr id="4" name="Freeform 6"><a:extLst><a:ext uri="{FF2B5EF4-FFF2-40B4-BE49-F238E27FC236}"><a16:creationId xmlns:a16="http://schemas.microsoft.com/office/drawing/2014/main" id="{810D3A6A-AB68-D6FF-85B7-4EB523E57F52}"/></a:ext></a:extLst></p:cNvPr><p:cNvSpPr/><p:nvPr/></p:nvSpPr><p:spPr><a:xfrm><a:off x="762000" y="9086850"/><a:ext cx="1321866" cy="342900"/></a:xfrm><a:custGeom><a:avLst/><a:gdLst/><a:ahLst/><a:cxnLst/><a:rect l="l" t="t" r="r" b="b"/><a:pathLst><a:path w="1321866" h="342900"><a:moveTo><a:pt x="0" y="0"/></a:moveTo><a:lnTo><a:pt x="1321866" y="0"/></a:lnTo><a:lnTo><a:pt x="1321866" y="342900"/></a:lnTo><a:lnTo><a:pt x="0" y="342900"/></a:lnTo><a:lnTo><a:pt x="0" y="0"/></a:lnTo><a:close/></a:path></a:pathLst></a:custGeom><a:blipFill><a:blip r:embed="rId3"/><a:stretch><a:fillRect l="-13374" t="-77864" r="-13198" b="-76659"/></a:stretch></a:blipFill><a:ln cap="sq"><a:noFill/><a:prstDash val="solid"/><a:miter/></a:ln></p:spPr><p:txBody><a:bodyPr/><a:lstStyle/><a:p><a:endParaRPr lang="en-SG"/></a:p></p:txBody></p:sp><p:sp><p:nvSpPr><p:cNvPr id="6" name="AutoShape 2"><a:extLst><a:ext uri="{FF2B5EF4-FFF2-40B4-BE49-F238E27FC236}"><a16:creationId xmlns:a16="http://schemas.microsoft.com/office/drawing/2014/main" id="{0A80EF3A-2C78-19EF-0FC5-017D8CAEAA04}"/></a:ext></a:extLst></p:cNvPr><p:cNvSpPr/><p:nvPr/></p:nvSpPr><p:spPr><a:xfrm><a:off x="609600" y="419100"/><a:ext cx="0" cy="857250"/></a:xfrm><a:prstGeom prst="line"><a:avLst/></a:prstGeom><a:ln w="38100" cap="flat"><a:solidFill><a:srgbClr val="2BBFB0"/></a:solidFill><a:prstDash val="solid"/><a:headEnd type="none" w="sm" len="sm"/><a:tailEnd type="none" w="sm" len="sm"/></a:ln></p:spPr><p:txBody><a:bodyPr/><a:lstStyle/><a:p><a:endParaRPr lang="en-SG"/></a:p></p:txBody></p:sp></p:spTree></p:cSld><p:clrMapOvr><a:masterClrMapping/></p:clrMapOvr></p:sld>